README.md
setup.py
pygams/__init__.py
pygams/defaults.py
pygams/fitness.py
pygams/helpers.py
pygams/mate.py
pygams/populations.py
pygams/pygams.py
pygams/rng.py
pygams/space.py
pygams.egg-info/PKG-INFO
pygams.egg-info/SOURCES.txt
pygams.egg-info/dependency_links.txt
pygams.egg-info/requires.txt
pygams.egg-info/top_level.txt