Metadata-Version: 2.1
Name: pygams
Version: 0.0.1
Summary: Implements a genetic algorithm to aid in model selection
Author: Samuel York
